LICENSE
MANIFEST.in
README.rst
setup.cfg
setup.py
setupdeps.py
test-requirements.txt
file_metadata/VERSION
file_metadata/__init__.py
file_metadata/_compat.py
file_metadata/generic_file.py
file_metadata/mixins.py
file_metadata/utilities.py
file_metadata.egg-info/PKG-INFO
file_metadata.egg-info/SOURCES.txt
file_metadata.egg-info/dependency_links.txt
file_metadata.egg-info/entry_points.txt
file_metadata.egg-info/requires.txt
file_metadata.egg-info/top_level.txt
file_metadata/application/__init__.py
file_metadata/application/application_file.py
file_metadata/audio/__init__.py
file_metadata/audio/audio_file.py
file_metadata/datafiles/core-3.2.1.jar
file_metadata/datafiles/javase-3.2.1.jar
file_metadata/datafiles/jcommander-1.48.jar
file_metadata/image/__init__.py
file_metadata/image/image_file.py
file_metadata/image/jpeg_file.py
file_metadata/image/svg_file.py
file_metadata/image/tiff_file.py
file_metadata/image/xcf_file.py
file_metadata/video/__init__.py
file_metadata/video/video_file.py
file_metadata/wikibot/__init__.py
file_metadata/wikibot/generate_user_files.py
file_metadata/wikibot/log_bot.py
file_metadata/wikibot/simple_bot.py