Metadata-Version: 1.1
Name: file-metadata
Version: 0.2.0
Summary: Helps to find structured metadata from a given file.
Home-page: https://github.com/AbdealiJK/file-metadata
Author: AbdealiJK
Author-email: abdealikothari@gmail.com
License: MIT
Platform: UNKNOWN
Classifier: Development Status :: 4 - Beta
Classifier: Environment :: Console
Classifier: Environment :: MacOS X
Classifier: Environment :: Win32 (MS Windows)
Classifier: Intended Audience :: Developers
Classifier: Operating System :: OS Independent
Classifier: Programming Language :: Python :: Implementation :: CPython
